odoo/addons/l10n_br_purchase_stock/README.rst
odoo/addons/l10n_br_purchase_stock/__init__.py
odoo/addons/l10n_br_purchase_stock/__manifest__.py
odoo/addons/l10n_br_purchase_stock/demo/purchase_order.xml
odoo/addons/l10n_br_purchase_stock/i18n/l10n_br_purchase_stock.pot
odoo/addons/l10n_br_purchase_stock/i18n/pt_BR.po
odoo/addons/l10n_br_purchase_stock/migrations/14.0.2.0.0/pre-migration.py
odoo/addons/l10n_br_purchase_stock/models/__init__.py
odoo/addons/l10n_br_purchase_stock/models/purchase_order.py
odoo/addons/l10n_br_purchase_stock/models/purchase_order_line.py
odoo/addons/l10n_br_purchase_stock/models/res_company.py
odoo/addons/l10n_br_purchase_stock/models/res_config_settings.py
odoo/addons/l10n_br_purchase_stock/models/stock_move.py
odoo/addons/l10n_br_purchase_stock/models/stock_picking.py
odoo/addons/l10n_br_purchase_stock/models/stock_rule.py
odoo/addons/l10n_br_purchase_stock/readme/CONFIGURE.rst
odoo/addons/l10n_br_purchase_stock/readme/CONTRIBUTORS.rst
odoo/addons/l10n_br_purchase_stock/readme/CREDITS.rst
odoo/addons/l10n_br_purchase_stock/readme/DESCRIPTION.rst
odoo/addons/l10n_br_purchase_stock/readme/HISTORY.rst
odoo/addons/l10n_br_purchase_stock/readme/INSTALL.rst
odoo/addons/l10n_br_purchase_stock/readme/ROADMAP.rst
odoo/addons/l10n_br_purchase_stock/readme/USAGE.rst
odoo/addons/l10n_br_purchase_stock/static/description/icon.png
odoo/addons/l10n_br_purchase_stock/static/description/index.html
odoo/addons/l10n_br_purchase_stock/tests/__init__.py
odoo/addons/l10n_br_purchase_stock/tests/test_l10n_br_purchase_stock.py
odoo/addons/l10n_br_purchase_stock/tests/test_l10n_br_purchase_stock_lp.py
odoo/addons/l10n_br_purchase_stock/tests/test_l10n_br_purchase_stock_sn.py
odoo/addons/l10n_br_purchase_stock/tests/test_stock_rule.py
odoo/addons/l10n_br_purchase_stock/views/purchase_order.xml
odoo/addons/l10n_br_purchase_stock/views/res_company_view.xml
odoo/addons/l10n_br_purchase_stock/views/res_config_settings.xml
odoo14_addon_l10n_br_purchase_stock-14.0.3.2.0.dist-info/METADATA
odoo14_addon_l10n_br_purchase_stock-14.0.3.2.0.dist-info/WHEEL
odoo14_addon_l10n_br_purchase_stock-14.0.3.2.0.dist-info/top_level.txt
odoo14_addon_l10n_br_purchase_stock-14.0.3.2.0.dist-info/RECORD
