Metadata-Version: 2.1
Name: odoo14-addon-l10n_br_purchase_stock
Version: 14.0.3.2.0
Summary: Brazilian Localization Purchase Stock
Home-page: https://github.com/OCA/l10n-brazil
Author: Akretion, Odoo Community Association (OCA)
Author-email: support@odoo-community.org
License: AGPL-3
Classifier: Programming Language :: Python
Classifier: Framework :: Odoo
Classifier: Framework :: Odoo :: 14.0
Classifier: License :: OSI Approved :: GNU Affero General Public License v3
Requires-Python: >=3.6
Requires-Dist: odoo14-addon-l10n-br-purchase
Requires-Dist: odoo14-addon-l10n-br-stock-account
Requires-Dist: odoo<14.1dev,>=14.0a
